dyma/__init__.py
dyma/dymaAction.py
dyma/dymaCore.py
dyma/dymaHandler.py
dyma/util.py
dyma/features/__init__.py
dyma-0.1.1.dist-info/LICENSE
dyma-0.1.1.dist-info/METADATA
dyma-0.1.1.dist-info/WHEEL
dyma-0.1.1.dist-info/top_level.txt
dyma-0.1.1.dist-info/RECORD
