Metadata-Version: 2.1
Name: dyma
Version: 0.1.1
Summary: Your Dynalist Manager.
Author: peisong13
Project-URL: Homepage, https://github.com/peisong13/Dyma
Project-URL: Bug Tracker, https://github.com/peisong13/Dyma/issues
Classifier: Programming Language :: Python :: 3
Classifier: License :: OSI Approved :: MIT License
Classifier: Operating System :: OS Independent
Requires-Python: >=3.9
License-File: LICENSE
